{
    "id": 94156085,
    "name": "Cognition",
    "author": "Endlevel",
    "creators": ["benji8080", "Endlevel"],
    "verifier": "swiborg",
    "verification": "https://www.youtube.com/watch?v=eSnYHNssMhQ",
    "percentToQualify": "100",
    "password": "Free to Copy",
    "records": [
        {
            "user": "stillsouless",
            "link": "https://www.youtube.com/watch?v=QuyKHg-qkLU",
            "percent": 100,
            "hz": 360
        },
        {
            "user": "Teno",
            "link": "https://www.youtube.com/watch?v=O5jhVGgDsB0",
            "percent": 100,
            "hz": 360
        },
        {
            "user": "Gokill",
            "link": "https://www.youtube.com/watch?v=wb-FsXdlFtg",
            "percent": 100,
            "hz": 360
        },
        {
            "user": "kloone",
            "link": "https://www.youtube.com/watch?v=kPksAsNIgAw",
            "percent": 100,
            "hz": 360
        },
        {
            "user": "Yeshy",
            "link": "https://www.youtube.com/watch?v=D_sMIi9ZkyE",
            "percent": 100,
            "hz": 360
        },
        {
            "user": "Tunax",
            "link": "https://www.youtube.com/watch?v=kmzNencTGhk",
            "percent": 100,
            "hz": 360
        },
        {
            "user": "Zeroxy",
            "link": "https://www.youtube.com/watch?v=w6lIuvVPnr4",
            "percent": 100,
            "hz": 360
        },
        {
            "user": "AlecZD",
            "link": "https://www.youtube.com/watch?v=9VoBwGE58qU",
            "percent": 100,
            "hz": 360
        },
        {
            "user": "A6",
            "link": "https://www.youtube.com/watch?v=yy88SH0-Cgk",
            "percent": 100,
            "hz": 360
        },
        {
            "user": "PoCle",
            "link": "https://www.youtube.com/watch?v=yYgcFBjP2RY",
            "percent": 100,
            "hz": 360
        },
        {
            "user": "Superjavicon",
            "link": "https://www.youtube.com/watch?v=nHuO6VwrFtU",
            "percent": 100,
            "hz": 360
        },
        {
            "user": "Bracus",
            "link": "https://www.youtube.com/watch?v=lKS6MO9xX4E",
            "percent": 100,
            "hz": 360
        },
        {
            "user": "Slaughter",
            "link": "https://www.youtube.com/watch?v=J8xklRPOlek",
            "percent": 100,
            "hz": 360
        },
        {
            "user": "Beastular",
            "link": "https://www.youtube.com/watch?v=yrjPAlOZPsc",
            "percent": 100,
            "hz": 360
        },
        {
            "user": "Dovi",
            "link": "https://www.youtube.com/watch?v=qve1yR5vodM",
            "percent": 100,
            "hz": 360
        },
        {
            "user": "Tihra",
            "link": "https://www.youtube.com/watch?v=gm-MujaNrHo",
            "percent": 100,
            "hz": 360
        },
        {
            "user": "tiredfish",
            "link": "https://www.youtube.com/watch?v=8IL13RIol_c",
            "percent": 100,
            "hz": 360
        },
        {
            "user": "Dogboi",
            "link": "https://www.youtube.com/watch?v=uI4j0a62IYU",
            "percent": 100,
            "hz": 360
        },
        {
            "user": "Cuatrocientos",
            "link": "https://www.youtube.com/watch?v=RTSnFEb1Wqc",
            "percent": 100,
            "hz": 360
        }
    ]
}
